arrow_sdk.py
constants.py
utilities.py
arrow_sdk/__init__.py
arrow_sdk/arrow_sdk.py
arrow_sdk/constants.py
arrow_sdk/utilities.py
arrow_sdk/abis/IERC20Metadata.json
arrow_sdk/abis/competition/ArrowOptionChainProxy.json
arrow_sdk/abis/competition/ArrowRegistry.json
arrow_sdk/abis/competition/IArrowEvents.json
arrow_sdk/abis/competition/IArrowRouter.json
arrow_sdk/abis/v4/ArrowOptionChainProxy.json
arrow_sdk/abis/v4/IArrowEvents.json
arrow_sdk/abis/v4/IArrowRegistry.json
arrow_sdk/abis/v4/IArrowRouter.json
arrow_sdk-1.0.17.dist-info/METADATA
arrow_sdk-1.0.17.dist-info/WHEEL
arrow_sdk-1.0.17.dist-info/top_level.txt
arrow_sdk-1.0.17.dist-info/RECORD
