Metadata-Version: 2.1
Name: arrow-sdk
Version: 1.0.17
Summary: UNKNOWN
Home-page: UNKNOWN
Author: Arrow Markets
Author-email: UNKNOWN
License: UNKNOWN
Platform: UNKNOWN
Requires-Dist: eth-account
Requires-Dist: eth-utils
Requires-Dist: pytz
Requires-Dist: requests
Requires-Dist: web3
